aiohttp_xmlrpc/__init__.py
aiohttp_xmlrpc/client.py
aiohttp_xmlrpc/common.py
aiohttp_xmlrpc/exceptions.py
aiohttp_xmlrpc/handler.py
aiohttp_xmlrpc/pytest_plugin.py
aiohttp_xmlrpc/xmlrpc.rng
aiohttp_xmlrpc-1.5.0.dist-info/LICENSE
aiohttp_xmlrpc-1.5.0.dist-info/METADATA
aiohttp_xmlrpc-1.5.0.dist-info/WHEEL
aiohttp_xmlrpc-1.5.0.dist-info/top_level.txt
aiohttp_xmlrpc-1.5.0.dist-info/RECORD
