Metadata-Version: 2.1
Name: aiohttp-xmlrpc
Version: 1.5.0
Summary: aiohttp XML-RPC server handler and client
Home-page: UNKNOWN
Author: Dmitry Orlov <me@mosquito.su>
License: MIT
Project-URL: Source, https://github.com/mosquito/aiohttp-xmlrpc
Platform: all
Classifier: Environment :: Console
Classifier: Programming Language :: Python :: 3
Classifier: Programming Language :: Python :: 3 :: Only
Classifier: Programming Language :: Python :: 3.6
Classifier: Programming Language :: Python :: 3.7
Classifier: Programming Language :: Python :: 3.8
Classifier: Programming Language :: Python :: 3.9
Classifier: Programming Language :: Python :: 3.10
Requires-Python: >=3.6
Provides-Extra: develop
License-File: LICENSE
